graphql32
