Metadata-Version: 2.1
Name: graphql32
Version: 1.8.3
Summary: graphql Python.
Author: Pain
Author-email: benjaminrodriguezshhh@proton.me
